airflow_provider_sap_hana/__init__.py
airflow_provider_sap_hana/get_provider_info.py
airflow_provider_sap_hana/hooks/__init__.py
airflow_provider_sap_hana/hooks/decorators.py
airflow_provider_sap_hana/hooks/hana.py
airflow_provider_sap_hana-1.4.0.dist-info/entry_points.txt
airflow_provider_sap_hana-1.4.0.dist-info/licenses/LICENSE
airflow_provider_sap_hana-1.4.0.dist-info/WHEEL
airflow_provider_sap_hana-1.4.0.dist-info/METADATA
airflow_provider_sap_hana-1.4.0.dist-info/RECORD
